odoo8_addon_website_country_localized_pages-8.0.1.0.0-py2.7-nspkg.pth
odoo_addons/website_country_localized_pages/ir_ui_view.py
odoo_addons/website_country_localized_pages/__openerp__.py
odoo_addons/website_country_localized_pages/ir_ui_view_view.xml
odoo_addons/website_country_localized_pages/__init__.py
odoo_addons/website_country_localized_pages/README.rst
odoo_addons/website_country_localized_pages/security/ir.model.access.csv
odoo_addons/website_country_localized_pages/i18n/nl_NL.po
odoo_addons/website_country_localized_pages/i18n/ru.po
odoo_addons/website_country_localized_pages/i18n/pt.po
odoo_addons/website_country_localized_pages/i18n/it.po
odoo_addons/website_country_localized_pages/i18n/es.po
odoo_addons/website_country_localized_pages/i18n/ro.po
odoo_addons/website_country_localized_pages/i18n/tr.po
odoo_addons/website_country_localized_pages/i18n/gl.po
odoo_addons/website_country_localized_pages/i18n/ca.po
odoo_addons/website_country_localized_pages/i18n/sl.po
odoo_addons/website_country_localized_pages/i18n/es_ES.po
odoo_addons/website_country_localized_pages/i18n/pt_PT.po
odoo_addons/website_country_localized_pages/i18n/nl.po
odoo_addons/website_country_localized_pages/i18n/am.po
odoo_addons/website_country_localized_pages/i18n/de.po
odoo_addons/website_country_localized_pages/i18n/fr.po
odoo_addons/website_country_localized_pages/i18n/pt_BR.po
odoo_addons/website_country_localized_pages/i18n/el_GR.po
odoo_addons/website_country_localized_pages/i18n/fi.po
odoo_addons/website_country_localized_pages/controllers/main.py
odoo_addons/website_country_localized_pages/controllers/__init__.py
odoo_addons/website_country_localized_pages/static/description/icon.png
odoo8_addon_website_country_localized_pages-8.0.1.0.0.dist-info/top_level.txt
odoo8_addon_website_country_localized_pages-8.0.1.0.0.dist-info/WHEEL
odoo8_addon_website_country_localized_pages-8.0.1.0.0.dist-info/RECORD
odoo8_addon_website_country_localized_pages-8.0.1.0.0.dist-info/metadata.json
odoo8_addon_website_country_localized_pages-8.0.1.0.0.dist-info/DESCRIPTION.rst
odoo8_addon_website_country_localized_pages-8.0.1.0.0.dist-info/METADATA
odoo8_addon_website_country_localized_pages-8.0.1.0.0.dist-info/namespace_packages.txt
