Metadata-Version: 2.0
Name: odoo8-addon-website-country-localized-pages
Version: 8.0.1.0.0
Summary: Show website pages localized according to country's visitor
Home-page: http://www.agilebg.com
Author: UNKNOWN
Author-email: UNKNOWN
License: AGPL-3
Platform: UNKNOWN
Requires-Dist: ipwhois
Requires-Dist: odoo (<9.0a,>=8.0a)
Classifier: Programming Language :: Python :: 2.7
Classifier: Framework :: Odoo
Classifier: License :: OSI Approved :: GNU Affero General Public License v3
